allneo/__init__.py
allneo/count_operations.py
allneo-17.0.0.dist-info/LICENSE.txt
allneo-17.0.0.dist-info/METADATA
allneo-17.0.0.dist-info/WHEEL
allneo-17.0.0.dist-info/top_level.txt
allneo-17.0.0.dist-info/RECORD
