Metadata-Version: 2.1
Name: allneo
Version: 17.0.0
Summary: complete package for neo4j developed by Roni Das
Home-page: https://github.com/pypa/sampleproject
Author: RONI DAS
Author-email: roni@totaltechnology.in
License: UNKNOWN
Platform: UNKNOWN
Classifier: Programming Language :: Python :: 3
Classifier: License :: OSI Approved :: MIT License
Classifier: Operating System :: OS Independent
Requires-Python: >=3.7
Requires-Dist: neo4j
